{
  "correspondences": [
    {
      "image_point": {
        "x": 479.368956689749,
        "y": 497.969796127873
      },
      "field_point": {
        "x": 21,
        "y": 120
      },
      "yard_marker_info": {
        "label": "nl4",
        "yard_line": 40,
        "hash_side": "l",
        "near_far": "n",
        "confidence": 0.8422428668334925
      }
    },
    {
      "image_point": {
        "x": 40.049472656932025,
        "y": 52.667810248999544
      },
      "field_point": {
        "x": 21,
        "y": 30
      },
      "yard_marker_info": {
        "label": "fl1",
        "yard_line": 10,
        "hash_side": "l",
        "near_far": "f",
        "confidence": 0.8517520411629077
      }
    },
    {
      "image_point": {
        "x": 237.66993965017815,
        "y": 72.24627817860863
      },
      "field_point": {
        "x": 21,
        "y": 60
      },
      "yard_marker_info": {
        "label": "fl2",
        "yard_line": 20,
        "hash_side": "l",
        "near_far": "f",
        "confidence": 0.8112593757750995
      }
    },
    {
      "image_point": {
        "x": 142.34291251539105,
        "y": 479.3127369273172
      },
      "field_point": {
        "x": 21,
        "y": 90
      },
      "yard_marker_info": {
        "label": "nl3",
        "yard_line": 30,
        "hash_side": "l",
        "near_far": "n",
        "confidence": 0.7988985159096056
      }
    },
    {
      "image_point": {
        "x": 436.0469956407301,
        "y": 83.60133291961687
      },
      "field_point": {
        "x": 21,
        "y": 90
      },
      "yard_marker_info": {
        "label": "fl3",
        "yard_line": 30,
        "hash_side": "l",
        "near_far": "f",
        "confidence": 0.7450670217847083
      }
    },
    {
      "image_point": {
        "x": 636.3723178491689,
        "y": 90.75912468514471
      },
      "field_point": {
        "x": 21,
        "y": 120
      },
      "yard_marker_info": {
        "label": "fl4",
        "yard_line": 40,
        "hash_side": "l",
        "near_far": "f",
        "confidence": 0.7092856475025465
      }
    },
    {
      "image_point": {
        "x": 226.1884765625,
        "y": 565.2513427734375
      },
      "field_point": {
        "x": 21,
        "y": 60
      },
      "yard_marker_info": {
        "label": "nl2",
        "yard_line": 20,
        "hash_side": "l",
        "near_far": "n",
        "confidence": 0.881009042263031
      }
    }
  ],
  "metadata": {
    "total_points": 7,
    "field_dimensions": {
      "length_ft": 360,
      "width_ft": 160,
      "hash_distance_ft": 40
    },
    "ncaa_standards": {
      "yard_marker_height_ft": 6,
      "yard_marker_width_ft": 4,
      "yard_marker_top_distance_ft": 27
    }
  }
}